databeam_mcap_reader/__init__.py
databeam_mcap_reader/__init__.pyi
databeam_mcap_reader/_core.cp312-win_amd64.pyd
databeam_mcap_reader/collector.py
databeam_mcap_reader/mcap_cli.exe
databeam_mcap_reader/reader.py
databeam_mcap_reader-0.5.1.dist-info/METADATA
databeam_mcap_reader-0.5.1.dist-info/WHEEL
databeam_mcap_reader-0.5.1.dist-info/licenses/LICENSE.txt
databeam_mcap_reader-0.5.1.dist-info/RECORD
