Metadata-Version: 2.4
Name: databeam-mcap-reader
Version: 0.5.1
Summary: MCAP file reader for JSON data implemented in C++ and Python.
Author-Email: VIRTUAL VEHICLE Research GmbH <peter.sammer@v2c2.at>
License-Expression: MIT
License-File: LICENSE.txt
Project-URL: Bug Tracker, https://github.com/virtual-vehicle/databeam/issues
Project-URL: Source, https://github.com/virtual-vehicle/databeam/tree/main/tools/databeam_mcap_reader
Project-URL: Documentation, https://github.com/virtual-vehicle/databeam/tree/main/tools/databeam_mcap_reader/README.md
Requires-Python: >=3.10
Requires-Dist: numpy
Requires-Dist: mcap
Requires-Dist: orjson
Requires-Dist: requests
